[
  {
    "event_type": "down",
    "name": "o",
    "time": 1742370679.495494
  },
  {
    "event_type": "up",
    "name": "o",
    "time": 1742370679.6439219
  },
  {
    "event_type": "down",
    "name": "t",
    "time": 1742370679.739598
  },
  {
    "event_type": "up",
    "name": "t",
    "time": 1742370679.834553
  },
  {
    "event_type": "down",
    "name": "h",
    "time": 1742370679.894801
  },
  {
    "event_type": "up",
    "name": "h",
    "time": 1742370679.946133
  },
  {
    "event_type": "down",
    "name": "e",
    "time": 1742370680.070518
  },
  {
    "event_type": "down",
    "name": "r",
    "time": 1742370680.1456409
  },
  {
    "event_type": "up",
    "name": "e",
    "time": 1742370680.173298
  },
  {
    "event_type": "up",
    "name": "r",
    "time": 1742370680.239079
  },
  {
    "event_type": "down",
    "name": "Key.space",
    "time": 1742370680.305847
  },
  {
    "event_type": "up",
    "name": "Key.space",
    "time": 1742370680.417519
  },
  {
    "event_type": "down",
    "name": "n",
    "time": 1742370680.553783
  },
  {
    "event_type": "up",
    "name": "n",
    "time": 1742370680.617153
  },
  {
    "event_type": "down",
    "name": "a",
    "time": 1742370680.6284
  },
  {
    "event_type": "up",
    "name": "a",
    "time": 1742370680.71359
  },
  {
    "event_type": "down",
    "name": "t",
    "time": 1742370680.8889909
  },
  {
    "event_type": "up",
    "name": "t",
    "time": 1742370681.022927
  },
  {
    "event_type": "down",
    "name": "i",
    "time": 1742370681.027818
  },
  {
    "event_type": "down",
    "name": "o",
    "time": 1742370681.106687
  },
  {
    "event_type": "up",
    "name": "i",
    "time": 1742370681.140397
  },
  {
    "event_type": "up",
    "name": "o",
    "time": 1742370681.196355
  },
  {
    "event_type": "down",
    "name": "n",
    "time": 1742370681.309888
  },
  {
    "event_type": "up",
    "name": "n",
    "time": 1742370681.439187
  },
  {
    "event_type": "down",
    "name": "Key.space",
    "time": 1742370681.4392772
  },
  {
    "event_type": "up",
    "name": "Key.space",
    "time": 1742370681.57758
  },
  {
    "event_type": "down",
    "name": "o",
    "time": 1742370681.94078
  },
  {
    "event_type": "down",
    "name": "u",
    "time": 1742370682.1200142
  },
  {
    "event_type": "up",
    "name": "o",
    "time": 1742370682.122995
  },
  {
    "event_type": "up",
    "name": "u",
    "time": 1742370682.239585
  },
  {
    "event_type": "down",
    "name": "t",
    "time": 1742370682.288842
  },
  {
    "event_type": "up",
    "name": "t",
    "time": 1742370682.3895621
  },
  {
    "event_type": "down",
    "name": "Key.space",
    "time": 1742370682.546599
  },
  {
    "event_type": "up",
    "name": "Key.space",
    "time": 1742370682.6833248
  },
  {
    "event_type": "down",
    "name": "a",
    "time": 1742370682.971658
  },
  {
    "event_type": "up",
    "name": "a",
    "time": 1742370683.083204
  },
  {
    "event_type": "down",
    "name": "f",
    "time": 1742370683.117439
  },
  {
    "event_type": "up",
    "name": "f",
    "time": 1742370683.165338
  },
  {
    "event_type": "down",
    "name": "t",
    "time": 1742370683.2772539
  },
  {
    "event_type": "up",
    "name": "t",
    "time": 1742370683.341283
  },
  {
    "event_type": "down",
    "name": "e",
    "time": 1742370683.378098
  },
  {
    "event_type": "up",
    "name": "e",
    "time": 1742370683.466294
  },
  {
    "event_type": "down",
    "name": "r",
    "time": 1742370683.547287
  },
  {
    "event_type": "up",
    "name": "r",
    "time": 1742370683.643559
  },
  {
    "event_type": "down",
    "name": "Key.space",
    "time": 1742370683.6823082
  },
  {
    "event_type": "up",
    "name": "Key.space",
    "time": 1742370683.790565
  },
  {
    "event_type": "down",
    "name": "f",
    "time": 1742370684.015948
  },
  {
    "event_type": "up",
    "name": "f",
    "time": 1742370684.091437
  },
  {
    "event_type": "down",
    "name": "a",
    "time": 1742370684.14013
  },
  {
    "event_type": "up",
    "name": "a",
    "time": 1742370684.2237
  },
  {
    "event_type": "down",
    "name": "c",
    "time": 1742370684.3818681
  },
  {
    "event_type": "up",
    "name": "c",
    "time": 1742370684.507304
  },
  {
    "event_type": "down",
    "name": "t",
    "time": 1742370684.51383
  },
  {
    "event_type": "up",
    "name": "t",
    "time": 1742370684.617763
  },
  {
    "event_type": "down",
    "name": "Key.space",
    "time": 1742370684.6568499
  },
  {
    "event_type": "up",
    "name": "Key.space",
    "time": 1742370684.7902038
  },
  {
    "event_type": "down",
    "name": "o",
    "time": 1742370684.9747882
  },
  {
    "event_type": "up",
    "name": "o",
    "time": 1742370685.106509
  },
  {
    "event_type": "down",
    "name": "w",
    "time": 1742370685.218817
  },
  {
    "event_type": "up",
    "name": "w",
    "time": 1742370685.346415
  },
  {
    "event_type": "down",
    "name": "n",
    "time": 1742370685.504585
  },
  {
    "event_type": "up",
    "name": "n",
    "time": 1742370685.692873
  },
  {
    "event_type": "down",
    "name": "Key.space",
    "time": 1742370685.780839
  },
  {
    "event_type": "up",
    "name": "Key.space",
    "time": 1742370685.936976
  },
  {
    "event_type": "down",
    "name": "s",
    "time": 1742370686.3377979
  },
  {
    "event_type": "down",
    "name": "t",
    "time": 1742370686.44885
  },
  {
    "event_type": "up",
    "name": "s",
    "time": 1742370686.46006
  },
  {
    "event_type": "up",
    "name": "t",
    "time": 1742370686.516876
  },
  {
    "event_type": "down",
    "name": "a",
    "time": 1742370686.6018581
  },
  {
    "event_type": "up",
    "name": "a",
    "time": 1742370686.709226
  },
  {
    "event_type": "down",
    "name": "n",
    "time": 1742370686.723646
  },
  {
    "event_type": "up",
    "name": "n",
    "time": 1742370686.833942
  },
  {
    "event_type": "down",
    "name": "d",
    "time": 1742370686.879672
  },
  {
    "event_type": "up",
    "name": "d",
    "time": 1742370686.975414
  },
  {
    "event_type": "down",
    "name": "Key.space",
    "time": 1742370687.098451
  },
  {
    "event_type": "up",
    "name": "Key.space",
    "time": 1742370687.226914
  },
  {
    "event_type": "down",
    "name": "n",
    "time": 1742370687.61356
  },
  {
    "event_type": "up",
    "name": "n",
    "time": 1742370687.697516
  },
  {
    "event_type": "down",
    "name": "u",
    "time": 1742370687.8285692
  },
  {
    "event_type": "up",
    "name": "u",
    "time": 1742370687.96192
  },
  {
    "event_type": "down",
    "name": "m",
    "time": 1742370688.035785
  },
  {
    "event_type": "up",
    "name": "m",
    "time": 1742370688.107501
  },
  {
    "event_type": "down",
    "name": "b",
    "time": 1742370688.246442
  },
  {
    "event_type": "up",
    "name": "b",
    "time": 1742370688.339187
  },
  {
    "event_type": "down",
    "name": "e",
    "time": 1742370688.35585
  },
  {
    "event_type": "up",
    "name": "e",
    "time": 1742370688.4443688
  },
  {
    "event_type": "down",
    "name": "r",
    "time": 1742370688.5256052
  },
  {
    "event_type": "up",
    "name": "r",
    "time": 1742370688.625629
  },
  {
    "event_type": "down",
    "name": "Key.space",
    "time": 1742370688.691648
  },
  {
    "event_type": "up",
    "name": "Key.space",
    "time": 1742370688.8229198
  },
  {
    "event_type": "down",
    "name": "t",
    "time": 1742370688.93579
  },
  {
    "event_type": "up",
    "name": "t",
    "time": 1742370689.039731
  },
  {
    "event_type": "down",
    "name": "h",
    "time": 1742370689.062805
  },
  {
    "event_type": "up",
    "name": "h",
    "time": 1742370689.167447
  },
  {
    "event_type": "down",
    "name": "e",
    "time": 1742370689.2455292
  },
  {
    "event_type": "up",
    "name": "e",
    "time": 1742370689.340147
  },
  {
    "event_type": "down",
    "name": "s",
    "time": 1742370689.462496
  },
  {
    "event_type": "up",
    "name": "s",
    "time": 1742370689.562419
  },
  {
    "event_type": "down",
    "name": "e",
    "time": 1742370689.6724238
  },
  {
    "event_type": "up",
    "name": "e",
    "time": 1742370689.7923682
  },
  {
    "event_type": "down",
    "name": "Key.space",
    "time": 1742370689.820493
  },
  {
    "event_type": "up",
    "name": "Key.space",
    "time": 1742370689.916336
  },
  {
    "event_type": "down",
    "name": "h",
    "time": 1742370689.988773
  },
  {
    "event_type": "up",
    "name": "h",
    "time": 1742370690.100327
  },
  {
    "event_type": "down",
    "name": "o",
    "time": 1742370690.115842
  },
  {
    "event_type": "up",
    "name": "o",
    "time": 1742370690.256756
  },
  {
    "event_type": "down",
    "name": "w",
    "time": 1742370690.4920828
  },
  {
    "event_type": "up",
    "name": "w",
    "time": 1742370690.605598
  },
  {
    "event_type": "down",
    "name": "e",
    "time": 1742370690.83151
  },
  {
    "event_type": "up",
    "name": "e",
    "time": 1742370690.931097
  },
  {
    "event_type": "down",
    "name": "v",
    "time": 1742370690.978327
  },
  {
    "event_type": "up",
    "name": "v",
    "time": 1742370691.046035
  },
  {
    "event_type": "down",
    "name": "e",
    "time": 1742370691.123716
  },
  {
    "event_type": "up",
    "name": "e",
    "time": 1742370691.222951
  },
  {
    "event_type": "down",
    "name": "r",
    "time": 1742370691.560639
  },
  {
    "event_type": "up",
    "name": "r",
    "time": 1742370691.655382
  },
  {
    "event_type": "down",
    "name": "Key.space",
    "time": 1742370691.9027379
  },
  {
    "event_type": "up",
    "name": "Key.space",
    "time": 1742370692.006975
  },
  {
    "event_type": "down",
    "name": "o",
    "time": 1742370692.1336691
  },
  {
    "event_type": "down",
    "name": "u",
    "time": 1742370692.25665
  },
  {
    "event_type": "up",
    "name": "o",
    "time": 1742370692.256819
  },
  {
    "event_type": "up",
    "name": "u",
    "time": 1742370692.372712
  },
  {
    "event_type": "down",
    "name": "t",
    "time": 1742370692.442605
  },
  {
    "event_type": "up",
    "name": "t",
    "time": 1742370692.5341609
  },
  {
    "event_type": "down",
    "name": "Key.space",
    "time": 1742370692.598679
  },
  {
    "event_type": "up",
    "name": "Key.space",
    "time": 1742370692.734574
  },
  {
    "event_type": "down",
    "name": "u",
    "time": 1742370693.216576
  },
  {
    "event_type": "up",
    "name": "u",
    "time": 1742370693.312332
  },
  {
    "event_type": "down",
    "name": "s",
    "time": 1742370693.387254
  },
  {
    "event_type": "up",
    "name": "s",
    "time": 1742370693.474315
  },
  {
    "event_type": "down",
    "name": "e",
    "time": 1742370693.596245
  },
  {
    "event_type": "up",
    "name": "e",
    "time": 1742370693.692294
  },
  {
    "event_type": "down",
    "name": "Key.space",
    "time": 1742370693.746552
  },
  {
    "event_type": "up",
    "name": "Key.space",
    "time": 1742370693.855736
  },
  {
    "event_type": "down",
    "name": "n",
    "time": 1742370694.69261
  },
  {
    "event_type": "up",
    "name": "n",
    "time": 1742370694.816212
  },
  {
    "event_type": "down",
    "name": "o",
    "time": 1742370695.4015281
  },
  {
    "event_type": "up",
    "name": "o",
    "time": 1742370695.48972
  },
  {
    "event_type": "down",
    "name": "w",
    "time": 1742370695.522881
  },
  {
    "event_type": "up",
    "name": "w",
    "time": 1742370695.6228359
  },
  {
    "event_type": "down",
    "name": "Key.space",
    "time": 1742370695.6560588
  },
  {
    "event_type": "up",
    "name": "Key.space",
    "time": 1742370695.783267
  },
  {
    "event_type": "down",
    "name": "p",
    "time": 1742370695.8713942
  },
  {
    "event_type": "up",
    "name": "p",
    "time": 1742370696.011345
  },
  {
    "event_type": "down",
    "name": "r",
    "time": 1742370696.049254
  },
  {
    "event_type": "up",
    "name": "r",
    "time": 1742370696.1414988
  },
  {
    "event_type": "down",
    "name": "e",
    "time": 1742370696.259497
  },
  {
    "event_type": "up",
    "name": "e",
    "time": 1742370696.347571
  },
  {
    "event_type": "down",
    "name": "s",
    "time": 1742370696.488692
  },
  {
    "event_type": "up",
    "name": "s",
    "time": 1742370696.5642
  },
  {
    "event_type": "down",
    "name": "e",
    "time": 1742370696.673646
  },
  {
    "event_type": "up",
    "name": "e",
    "time": 1742370696.793598
  },
  {
    "event_type": "down",
    "name": "n",
    "time": 1742370696.8586361
  },
  {
    "event_type": "up",
    "name": "n",
    "time": 1742370696.930078
  },
  {
    "event_type": "down",
    "name": "t",
    "time": 1742370696.9904609
  },
  {
    "event_type": "up",
    "name": "t",
    "time": 1742370697.099017
  },
  {
    "event_type": "down",
    "name": "Key.space",
    "time": 1742370697.182394
  },
  {
    "event_type": "up",
    "name": "Key.space",
    "time": 1742370697.3468149
  },
  {
    "event_type": "down",
    "name": "l",
    "time": 1742370697.62231
  },
  {
    "event_type": "up",
    "name": "l",
    "time": 1742370697.7229388
  },
  {
    "event_type": "down",
    "name": "a",
    "time": 1742370697.77682
  },
  {
    "event_type": "up",
    "name": "a",
    "time": 1742370697.897025
  },
  {
    "event_type": "down",
    "name": "s",
    "time": 1742370697.897311
  },
  {
    "event_type": "up",
    "name": "s",
    "time": 1742370697.9799879
  },
  {
    "event_type": "down",
    "name": "t",
    "time": 1742370698.0567281
  },
  {
    "event_type": "up",
    "name": "t",
    "time": 1742370698.116176
  },
  {
    "event_type": "down",
    "name": "Key.space",
    "time": 1742370698.258383
  },
  {
    "event_type": "up",
    "name": "Key.space",
    "time": 1742370698.4150221
  },
  {
    "event_type": "down",
    "name": "w",
    "time": 1742370698.540598
  },
  {
    "event_type": "up",
    "name": "w",
    "time": 1742370698.693399
  },
  {
    "event_type": "down",
    "name": "i",
    "time": 1742370698.76445
  },
  {
    "event_type": "up",
    "name": "i",
    "time": 1742370698.828565
  },
  {
    "event_type": "down",
    "name": "l",
    "time": 1742370698.949653
  },
  {
    "event_type": "up",
    "name": "l",
    "time": 1742370699.017466
  },
  {
    "event_type": "down",
    "name": "l",
    "time": 1742370699.056633
  },
  {
    "event_type": "up",
    "name": "l",
    "time": 1742370699.139553
  },
  {
    "event_type": "down",
    "name": "l",
    "time": 1742370699.283403
  },
  {
    "event_type": "up",
    "name": "l",
    "time": 1742370699.411951
  },
  {
    "event_type": "down",
    "name": "Key.space",
    "time": 1742370699.541632
  },
  {
    "event_type": "up",
    "name": "Key.space",
    "time": 1742370699.613312
  },
  {
    "event_type": "down",
    "name": "g",
    "time": 1742370699.694539
  },
  {
    "event_type": "up",
    "name": "g",
    "time": 1742370699.7979488
  },
  {
    "event_type": "down",
    "name": "o",
    "time": 1742370699.8604312
  },
  {
    "event_type": "down",
    "name": "Key.space",
    "time": 1742370699.963756
  },
  {
    "event_type": "up",
    "name": "o",
    "time": 1742370699.991343
  },
  {
    "event_type": "up",
    "name": "Key.space",
    "time": 1742370700.075734
  },
  {
    "event_type": "down",
    "name": "f",
    "time": 1742370700.910469
  },
  {
    "event_type": "up",
    "name": "f",
    "time": 1742370701.014027
  },
  {
    "event_type": "down",
    "name": "o",
    "time": 1742370701.1874912
  },
  {
    "event_type": "up",
    "name": "o",
    "time": 1742370701.279186
  },
  {
    "event_type": "down",
    "name": "l",
    "time": 1742370701.468469
  },
  {
    "event_type": "up",
    "name": "l",
    "time": 1742370701.527675
  },
  {
    "event_type": "down",
    "name": "l",
    "time": 1742370701.606173
  },
  {
    "event_type": "up",
    "name": "l",
    "time": 1742370701.675319
  },
  {
    "event_type": "down",
    "name": "o",
    "time": 1742370701.786418
  },
  {
    "event_type": "up",
    "name": "o",
    "time": 1742370701.873218
  },
  {
    "event_type": "down",
    "name": "w",
    "time": 1742370702.188656
  },
  {
    "event_type": "up",
    "name": "w",
    "time": 1742370702.275838
  },
  {
    "event_type": "down",
    "name": "Key.space",
    "time": 1742370702.343206
  },
  {
    "event_type": "up",
    "name": "Key.space",
    "time": 1742370702.4510689
  },
  {
    "event_type": "down",
    "name": "b",
    "time": 1742370702.896696
  },
  {
    "event_type": "up",
    "name": "b",
    "time": 1742370702.963765
  },
  {
    "event_type": "down",
    "name": "e",
    "time": 1742370703.011829
  },
  {
    "event_type": "up",
    "name": "e",
    "time": 1742370703.1073751
  },
  {
    "event_type": "down",
    "name": "f",
    "time": 1742370703.259449
  },
  {
    "event_type": "up",
    "name": "f",
    "time": 1742370703.367264
  },
  {
    "event_type": "down",
    "name": "o",
    "time": 1742370703.399225
  },
  {
    "event_type": "up",
    "name": "o",
    "time": 1742370703.483161
  },
  {
    "event_type": "down",
    "name": "r",
    "time": 1742370703.621512
  },
  {
    "event_type": "up",
    "name": "r",
    "time": 1742370703.756715
  },
  {
    "event_type": "down",
    "name": "e",
    "time": 1742370703.8052201
  },
  {
    "event_type": "up",
    "name": "e",
    "time": 1742370703.897457
  },
  {
    "event_type": "down",
    "name": "Key.space",
    "time": 1742370703.9912808
  },
  {
    "event_type": "up",
    "name": "Key.space",
    "time": 1742370704.10566
  },
  {
    "event_type": "down",
    "name": "a",
    "time": 1742370704.183454
  },
  {
    "event_type": "up",
    "name": "a",
    "time": 1742370704.2892458
  },
  {
    "event_type": "down",
    "name": "Key.backspace",
    "time": 1742370704.74858
  },
  {
    "event_type": "up",
    "name": "Key.backspace",
    "time": 1742370704.8287098
  },
  {
    "event_type": "down",
    "name": "e",
    "time": 1742370704.949526
  },
  {
    "event_type": "up",
    "name": "e",
    "time": 1742370705.0734231
  },
  {
    "event_type": "down",
    "name": "n",
    "time": 1742370705.163487
  },
  {
    "event_type": "up",
    "name": "n",
    "time": 1742370705.267693
  },
  {
    "event_type": "down",
    "name": "d",
    "time": 1742370705.3184252
  },
  {
    "event_type": "up",
    "name": "d",
    "time": 1742370705.41401
  },
  {
    "event_type": "down",
    "name": "Key.space",
    "time": 1742370705.5258
  },
  {
    "event_type": "up",
    "name": "Key.space",
    "time": 1742370705.625665
  },
  {
    "event_type": "down",
    "name": "w",
    "time": 1742370705.7003698
  },
  {
    "event_type": "up",
    "name": "w",
    "time": 1742370705.82287
  },
  {
    "event_type": "down",
    "name": "a",
    "time": 1742370705.922267
  },
  {
    "event_type": "up",
    "name": "a",
    "time": 1742370706.0233421
  },
  {
    "event_type": "down",
    "name": "y",
    "time": 1742370706.066047
  },
  {
    "event_type": "up",
    "name": "y",
    "time": 1742370706.149811
  },
  {
    "event_type": "down",
    "name": "Key.space",
    "time": 1742370706.156112
  },
  {
    "event_type": "up",
    "name": "Key.space",
    "time": 1742370706.31885
  },
  {
    "event_type": "down",
    "name": "w",
    "time": 1742370706.336816
  },
  {
    "event_type": "up",
    "name": "w",
    "time": 1742370706.457429
  },
  {
    "event_type": "down",
    "name": "o",
    "time": 1742370706.49012
  },
  {
    "event_type": "down",
    "name": "u",
    "time": 1742370706.584569
  },
  {
    "event_type": "up",
    "name": "o",
    "time": 1742370706.640023
  },
  {
    "event_type": "up",
    "name": "u",
    "time": 1742370706.6732318
  },
  {
    "event_type": "down",
    "name": "l",
    "time": 1742370706.7844448
  },
  {
    "event_type": "up",
    "name": "l",
    "time": 1742370706.936738
  },
  {
    "event_type": "down",
    "name": "d",
    "time": 1742370706.974346
  },
  {
    "event_type": "up",
    "name": "d",
    "time": 1742370707.09021
  },
  {
    "event_type": "down",
    "name": "Key.space",
    "time": 1742370707.188127
  },
  {
    "event_type": "up",
    "name": "Key.space",
    "time": 1742370707.308136
  },
  {
    "event_type": "down",
    "name": "a",
    "time": 1742370707.492655
  },
  {
    "event_type": "up",
    "name": "a",
    "time": 1742370707.592143
  },
  {
    "event_type": "down",
    "name": "g",
    "time": 1742370707.606962
  },
  {
    "event_type": "up",
    "name": "g",
    "time": 1742370707.675158
  },
  {
    "event_type": "down",
    "name": "a",
    "time": 1742370707.7248461
  },
  {
    "event_type": "up",
    "name": "a",
    "time": 1742370707.839668
  },
  {
    "event_type": "down",
    "name": "i",
    "time": 1742370707.856161
  },
  {
    "event_type": "down",
    "name": "n",
    "time": 1742370707.982684
  },
  {
    "event_type": "up",
    "name": "i",
    "time": 1742370708.0111868
  },
  {
    "event_type": "up",
    "name": "n",
    "time": 1742370708.107388
  },
  {
    "event_type": "down",
    "name": "t",
    "time": 1742370708.255362
  },
  {
    "event_type": "up",
    "name": "t",
    "time": 1742370708.391239
  },
  {
    "event_type": "down",
    "name": "Key.backspace",
    "time": 1742370708.8234282
  },
  {
    "event_type": "up",
    "name": "Key.backspace",
    "time": 1742370708.958954
  },
  {
    "event_type": "down",
    "name": "s",
    "time": 1742370709.104528
  },
  {
    "event_type": "up",
    "name": "s",
    "time": 1742370709.184007
  },
  {
    "event_type": "down",
    "name": "t",
    "time": 1742370709.297465
  },
  {
    "event_type": "up",
    "name": "t",
    "time": 1742370709.409225
  },
  {
    "event_type": "down",
    "name": "Key.space",
    "time": 1742370709.731663
  },
  {
    "event_type": "up",
    "name": "Key.space",
    "time": 1742370709.841177
  }
]